dbt_invoke/__init__.py
dbt_invoke/main.py
dbt_invoke/properties.py
dbt_invoke/internal/__init__.py
dbt_invoke/internal/_utils.py
dbt_invoke/internal/_version.py
dbt_invoke-1.0.0.dist-info/LICENSE
dbt_invoke-1.0.0.dist-info/METADATA
dbt_invoke-1.0.0.dist-info/WHEEL
dbt_invoke-1.0.0.dist-info/entry_points.txt
dbt_invoke-1.0.0.dist-info/top_level.txt
dbt_invoke-1.0.0.dist-info/RECORD
