Metadata-Version: 2.1
Name: dbt-invoke
Version: 1.0.0
Summary: dbt-invoke is a CLI for creating, updating, and deleting dbt property files.
Home-page: https://github.com/Dashlane/dbt-invoke
Author: Robert Astel, Jennifer Zhan, Vincent Dragonette
Author-email: rob.astel@gmail.com
License: Apache License 2.0
Platform: UNKNOWN
Requires-Python: >=3.7.0
Requires-Dist: invoke >=1.4.1
Requires-Dist: PyYAML >=5.1
Requires-Dist: ruamel.yaml >=0.17.12
